{
     "AMS 3": 21723,
     "AMS 5": 21735,
     "AMS 7": 21750,
     "AMS 7L": 22734,
     "AMS 10": 21756,
     "AMS 11A": 21566,
     "AMS 11B": 21578,
     "AMS 80A": 22859,
     "AMS 107": 22353,
     "AMS 114": 21775,
     "AMS 129": 23278,
     "AMS 131": 21769,
     "AMS 200": 22877,
     "AMS 203": 22961,
     "AMS 204": 23252,
     "AMS 211": 22765,
     "AMS 214": 22748,
     "AMS 217": 22760,
     "AMS 229": 23689,
     "AMS 263": 21777,
     "AMS 266A": 23253,
     "AMS 274": 21778,
     "AMS 280B": 24368,
     "AMS 280C": 22869,
     "ANTH 1": 20895,
     "ANTH 97": 23186,
     "ANTH 102A": 20916,
     "ANTH 104": 20917,
     "ANTH 110F": 23134,
     "ANTH 110I": 23257,
     "ANTH 110L": 23885,
     "ANTH 110Q": 23901,
     "ANTH 113": 22958,
     "ANTH 130A": 20918,
     "ANTH 130L": 20920,
     "ANTH 139": 20921,
     "ANTH 146": 20922,
     "ANTH 150": 20923,
     "ANTH 158": 22979,
     "ANTH 170": 20926,
     "ANTH 179": 23131,
     "ANTH 180": 20927,
     "ANTH 180L": 20928,
     "ANTH 194A": 22980,
     "ANTH 194H": 22946,
     "ANTH 194S": 20929,
     "ANTH 195A": 23091,
     "ANTH 200A": 20930,
     "ANTH 216": 22747,
     "ANTH 228": 20931,
     "ANTH 248": 22894,
     "ANTH 270A": 23139,
     "ANTH 272": 22963,
     "ANTH 280": 22703,
     "ANTH 280L": 22704,
     "ANTH 292": 20932,
     "ANTH 294R": 20933,
     "ANTH 295A": 24393,
     "APLX 80": 23136,
     "APLX 113": 22945,
     "APLX 190": 24418,
     "ART 10E": 23068,
     "ART 20I": 23077,
     "ART 20J": 23078,
     "ART 20K": 23137,
     "ART 80D": 20936,
     "ART 80F": 20945,
     "ART 106C": 23271,
     "ART 130": 20952,
     "ART 146T": 22891,
     "ART 150": 22928,
     "ART 156": 23085,
     "ART 162A": 20953,
     "ART 163A": 20954,
     "ART 180B": 20956,
     "ART 184": 23235,
     "ART 188": 20955,
     "ART 189": 20957,
     "ART 194": 20934,
     "ARTG 80G": 23169,
     "ARTG 80H": 23099,
     "ARTG 80I": 23058,
     "ARTG 118": 23038,
     "ARTG 129": 23223,
     "ARTG 170": 23183,
     "ARTG 179": 22997,
     "ASTR 1": 22902,
     "ASTR 2": 20958,
     "ASTR 111": 22927,
     "ASTR 119": 24357,
     "ASTR 135A": 22619,
     "ASTR 171": 22363,
     "ASTR 205": 20971,
     "ASTR 212": 20972,
     "ASTR 220A": 23936,
     "ASTR 223": 22878,
     "ASTR 292": 20973,
     "BIOC 100A": 20974,
     "BIOC 110L": 20981,
     "BIOE 20B": 21000,
     "BIOE 20C": 21020,
     "BIOE 82": 23182,
     "BIOE 107": 21098,
     "BIOE 109": 21113,
     "BIOE 124": 23009,
     "BIOE 124L": 23010,
     "BIOE 135": 23888,
     "BIOE 135L": 23890,
     "BIOE 136": 23290,
     "BIOE 140": 21093,
     "BIOE 145": 21109,
     "BIOE 145L": 21112,
     "BIOE 155": 22865,
     "BIOE 159A": 21103,
     "BIOE 159B": 21104,
     "BIOE 159C": 21105,
     "BIOE 159D": 21106,
     "BIOE 159E": 24298,
     "BIOE 165": 21107,
     "BIOE 172": 21057,
     "BIOE 172L": 21058,
     "BIOE 183W": 23019,
     "BIOE 200A": 21123,
     "BIOE 200B": 21122,
     "BIOE 245": 21124,
     "BIOE 245L": 21125,
     "BIOE 272": 21120,
     "BIOE 272L": 21121,
     "BIOE 281A": 21137,
     "BIOE 281B": 21138,
     "BIOE 281C": 21139,
     "BIOE 281D": 23221,
     "BIOE 281E": 23025,
     "BIOE 281F": 21140,
     "BIOE 281G": 23222,
     "BIOE 281H": 22951,
     "BIOE 281I": 22871,
     "BIOE 281K": 22872,
     "BIOE 281L": 21141,
     "BIOE 281N": 21142,
     "BIOE 281O": 22873,
     "BIOE 281P": 21143,
     "BIOE 281Q": 21144,
     "BIOE 281R": 21145,
     "BIOE 281S": 23024,
     "BIOE 281U": 21147,
     "BIOE 281V": 21148,
     "BIOE 281W": 21149,
     "BIOE 294": 21152,
     "BIOE 295": 24383,
     "BIOL 15": 20983,
     "BIOL 20A": 20984,
     "BIOL 20L": 21021,
     "BIOL 100": 21037,
     "BIOL 101L": 22929,
     "BIOL 102L": 23262,
     "BIOL 103L": 23920,
     "BIOL 105": 21046,
     "BIOL 109L": 21059,
     "BIOL 110": 21060,
     "BIOL 115L": 21068,
     "BIOL 125": 21078,
     "BIOL 130": 21083,
     "BIOL 130L": 21088,
     "BIOL 186F": 22651,
     "BIOL 186L": 22652,
     "BIOL 186R": 22985,
     "BIOL 189": 22637,
     "BIOL 189W": 22984,
     "BIOL 191": 22939,
     "BIOL 200A": 21118,
     "BIOL 201": 21119,
     "BIOL 217": 24371,
     "BIOL 280A": 21126,
     "BIOL 280B": 22750,
     "BIOL 280C": 22766,
     "BIOL 280D": 21127,
     "BIOL 280E": 22864,
     "BIOL 280F": 21128,
     "BIOL 280G": 23190,
     "BIOL 280H": 21129,
     "BIOL 280I": 22755,
     "BIOL 280J": 22636,
     "BIOL 280K": 21130,
     "BIOL 280L": 21131,
     "BIOL 280M": 22944,
     "BIOL 280N": 23191,
     "BIOL 280O": 21133,
     "BIOL 280P": 23895,
     "BIOL 280Q": 22767,
     "BIOL 280R": 23255,
     "BIOL 280S": 22768,
     "BIOL 280T": 21134,
     "BIOL 280U": 21135,
     "BIOL 280W": 21136,
     "BIOL 280Y": 22769,
     "BIOL 280Z": 23121,
     "BIOL 288": 23256,
     "BIOL 291": 21150,
     "BIOL 292": 21151,
     "BME 5": 22810,
     "BME 18": 23658,
     "BME 80G": 21236,
     "BME 110": 21154,
     "BME 122H": 22976,
     "BME 129A": 23207,
     "BME 130": 22660,
     "BME 132": 23237,
     "BME 140": 22838,
     "BME 185": 23771,
     "BME 205": 21153,
     "BME 232": 23251,
     "BME 280B": 21157,
     "BME 281C": 22959,
     "BME 281D": 23122,
     "BME 281E": 22962,
     "BME 281F": 24370,
     "BME 281H": 22656,
     "BME 281J": 24372,
     "BME 281N": 23215,
     "BME 281P": 22870,
     "BME 281R": 23243,
     "BME 281S": 22657,
     "BME 281V": 23135,
     "CHEM 1A": 21175,
     "CHEM 1B": 21180,
     "CHEM 1C": 21193,
     "CHEM 1M": 21206,
     "CHEM 1N": 21219,
     "CHEM 8A": 21250,
     "CHEM 8L": 21266,
     "CHEM 122": 21291,
     "CHEM 143": 21294,
     "CHEM 146A": 21297,
     "CHEM 163A": 21298,
     "CHEM 182": 22938,
     "CHEM 200A": 21305,
     "CHEM 234": 21306,
     "CHEM 242B": 23087,
     "CHEM 269": 22658,
     "CHEM 274": 22661,
     "CHEM 275": 22705,
     "CHEM 282": 21307,
     "CHEM 284": 21308,
     "CHEM 286": 21309,
     "CHEM 291": 23007,
     "CHEM 292": 21310,
     "CHEM 296": 21311,
     "CHIN 1": 21314,
     "CHIN 4": 21315,
     "CHIN 103": 21316,
     "CLNI 1": 23736,
     "CLNI 90": 23005,
     "CLNI 120": 23015,
     "CLTE 1": 23750,
     "CLTE 60": 23935,
     "CLTE 95": 22982,
     "CLTE 120": 23016,
     "CLTE 135": 23238,
     "CMMU 10": 21318,
     "CMMU 105A": 23338,
     "CMMU 105B": 23339,
     "CMMU 105C": 23340,
     "CMMU 132": 21324,
     "CMMU 149": 22613,
     "CMMU 161": 21321,
     "CMPE 3": 21327,
     "CMPE 8": 22722,
     "CMPE 12": 22626,
     "CMPE 12L": 21332,
     "CMPE 16": 21343,
     "CMPE 80A": 22745,
     "CMPE 80N": 21352,
     "CMPE 100": 21357,
     "CMPE 100L": 21358,
     "CMPE 110": 21363,
     "CMPE 118": 22627,
     "CMPE 118L": 22628,
     "CMPE 121": 21372,
     "CMPE 121L": 21373,
     "CMPE 129A": 23011,
     "CMPE 141": 21707,
     "CMPE 149": 23093,
     "CMPE 150": 21378,
     "CMPE 150L": 22851,
     "CMPE 185": 21384,
     "CMPE 200": 21385,
     "CMPE 202": 21386,
     "CMPE 216": 23004,
     "CMPE 218": 22828,
     "CMPE 218L": 22827,
     "CMPE 220": 23351,
     "CMPE 241": 22710,
     "CMPE 249": 23140,
     "CMPE 252A": 21387,
     "CMPE 264": 21388,
     "CMPE 280C": 22692,
     "CMPE 280N": 21390,
     "CMPE 280P": 21391,
     "CMPE 280S": 23273,
     "CMPE 280V": 22693,
     "CMPM 25": 22952,
     "CMPM 146": 22713,
     "CMPM 147": 23751,
     "CMPM 170": 22813,
     "CMPM 176": 23141,
     "CMPM 179": 22996,
     "CMPM 201": 23216,
     "CMPM 204": 24132,
     "CMPM 206": 23934,
     "CMPM 280G": 24351,
     "CMPM 280K": 23940,
     "CMPM 280X": 24405,
     "CMPM 290A": 23234,
     "CMPS 5J": 21406,
     "CMPS 5P": 22842,
     "CMPS 12A": 21392,
     "CMPS 12B": 21394,
     "CMPS 12L": 21395,
     "CMPS 12M": 22645,
     "CMPS 101": 21418,
     "CMPS 102": 21424,
     "CMPS 104A": 21429,
     "CMPS 109": 21433,
     "CMPS 111": 21441,
     "CMPS 112": 21445,
     "CMPS 115": 21451,
     "CMPS 121": 22998,
     "CMPS 128": 22668,
     "CMPS 130": 21452,
     "CMPS 142": 22685,
     "CMPS 160": 21456,
     "CMPS 160L": 22648,
     "CMPS 166A": 22832,
     "CMPS 180": 21457,
     "CMPS 183": 21461,
     "CMPS 185": 23094,
     "CMPS 200": 21463,
     "CMPS 201": 21464,
     "CMPS 217": 21469,
     "CMPS 223": 21470,
     "CMPS 242": 21471,
     "CMPS 260": 21477,
     "CMPS 266A": 23254,
     "CMPS 278": 22625,
     "CMPS 280D": 22770,
     "CMPS 280L": 23268,
     "CMPS 280M": 23192,
     "CMPS 280S": 21478,
     "CMPS 290S": 24335,
     "COWL 1": 23584,
     "COWL 70A": 20935,
     "COWL 107": 23017,
     "COWL 111": 22941,
     "COWL 122": 23195,
     "COWL 168": 22986,
     "COWL 184A": 21479,
     "CRES 10": 23040,
     "CRES 110Q": 23902,
     "CRES 199F": 24444,
     "CRSN 1": 23598,
     "CRSN 15": 23267,
     "CRSN 55": 23084,
     "CRSN 56": 23030,
     "CRSN 90": 21317,
     "CRSN 122": 23196,
     "CRSN 151C": 23245,
     "CRSN 152": 23250,
     "CRSN 162": 23057,
     "CRWN 1": 23673,
     "CRWN 3L": 23270,
     "CRWN 70": 22943,
     "CRWN 70L": 23258,
     "CRWN 86": 23187,
     "CRWN 88": 23260,
     "CRWN 90": 23199,
     "CRWN 92": 23886,
     "CRWN 185": 22662,
     "CSP 200": 24304,
     "CSP 210": 24303,
     "CSP 220": 24305,
     "CSP 230": 24380,
     "DANM 210": 23357,
     "DANM 219": 22616,
     "DANM 220": 22617,
     "DANM 250A": 22623,
     "DANM 250B": 22624,
     "DANM 250E": 23218,
     "EART 1": 23772,
     "EART 5": 21480,
     "EART 5L": 21489,
     "EART 96": 24339,
     "EART 101": 21495,
     "EART 101L": 21497,
     "EART 109": 21502,
     "EART 109L": 21504,
     "EART 110A": 21505,
     "EART 110L": 21508,
     "EART 111": 22696,
     "EART 116": 21509,
     "EART 119": 24360,
     "EART 121": 21516,
     "EART 135L": 23917,
     "EART 150": 21519,
     "EART 150L": 21521,
     "EART 160": 22746,
     "EART 190": 24369,
     "EART 191C": 23027,
     "EART 203": 21522,
     "EART 204": 22942,
     "EART 213": 22754,
     "EART 220": 21523,
     "EART 290B": 21525,
     "EART 290E": 21526,
     "EART 292": 21528,
     "ECON 1": 21529,
     "ECON 2": 21542,
     "ECON 10A": 21549,
     "ECON 11A": 21561,
     "ECON 11B": 21571,
     "ECON 20": 23209,
     "ECON 100A": 21590,
     "ECON 100B": 21595,
     "ECON 105": 21602,
     "ECON 111A": 21603,
     "ECON 113": 21613,
     "ECON 115": 21618,
     "ECON 117B": 21621,
     "ECON 119": 23361,
     "ECON 125": 24340,
     "ECON 126": 21625,
     "ECON 130": 21632,
     "ECON 133": 21633,
     "ECON 136": 21636,
     "ECON 140": 21639,
     "ECON 143": 21642,
     "ECON 161A": 21643,
     "ECON 166A": 22829,
     "ECON 170": 21644,
     "ECON 180": 21645,
     "ECON 186": 21646,
     "ECON 197": 22978,
     "ECON 200": 21647,
     "ECON 204A": 21650,
     "ECON 205A": 21651,
     "ECON 210B": 21652,
     "ECON 211A": 21653,
     "ECON 216": 21654,
     "ECON 220A": 21657,
     "ECON 221A": 22900,
     "ECON 233": 21658,
     "ECON 241A": 21661,
     "ECON 250A": 21662,
     "ECON 274": 22895,
     "ECON 275": 22983,
     "ECON 276": 24389,
     "ECON 294A": 21664,
     "EDUC 50B": 22784,
     "EDUC 50C": 22783,
     "EDUC 60": 22880,
     "EDUC 104": 22841,
     "EDUC 120": 21670,
     "EDUC 160": 21671,
     "EDUC 171": 22893,
     "EDUC 180": 21665,
     "EDUC 200": 21675,
     "EDUC 204": 22840,
     "EDUC 211": 22694,
     "EDUC 212A": 22896,
     "EDUC 220": 21676,
     "EDUC 222": 21678,
     "EDUC 226": 21680,
     "EDUC 228": 21679,
     "EDUC 230": 21677,
     "EDUC 232": 21681,
     "EDUC 235": 21672,
     "EDUC 262": 21682,
     "EE 80S": 22805,
     "EE 101": 21683,
     "EE 101L": 21684,
     "EE 103": 21691,
     "EE 103L": 22912,
     "EE 129A": 23013,
     "EE 130": 21692,
     "EE 130L": 21693,
     "EE 145": 21698,
     "EE 145L": 21701,
     "EE 154": 21712,
     "EE 172": 22727,
     "EE 173": 21379,
     "EE 173L": 21380,
     "EE 175": 22922,
     "EE 175L": 22918,
     "EE 183": 24293,
     "EE 216": 22876,
     "EE 221": 21718,
     "EE 227": 23119,
     "EE 230": 21719,
     "EE 241": 22711,
     "EE 251": 21721,
     "EE 261": 23768,
     "EE 280A": 23276,
     "EE 280B": 22771,
     "EE 280N": 23189,
     "EE 280O": 22751,
     "EE 280Z": 23277,
     "EE 290": 22716,
     "EE 293": 22709,
     "ENVS 15": 21779,
     "ENVS 24": 21780,
     "ENVS 80B": 21781,
     "ENVS 106A": 21782,
     "ENVS 115A": 21783,
     "ENVS 115L": 21789,
     "ENVS 120": 21790,
     "ENVS 121": 23887,
     "ENVS 130A": 21791,
     "ENVS 130L": 21795,
     "ENVS 141": 21796,
     "ENVS 145": 23246,
     "ENVS 158": 21797,
     "ENVS 167": 21798,
     "ENVS 167L": 22706,
     "ENVS 177": 22911,
     "ENVS 189": 22756,
     "ENVS 196": 23359,
     "ENVS 201A": 21799,
     "ENVS 215A": 22720,
     "ENVS 215L": 22721,
     "ENVS 290": 21800,
     "ENVS 290L": 21801,
     "ENVS 292": 24290,
     "ESCI 160": 24200,
     "FILM 20A": 21820,
     "FILM 80M": 23323,
     "FILM 80S": 22794,
     "FILM 132A": 21831,
     "FILM 134B": 21838,
     "FILM 150": 21851,
     "FILM 162": 21852,
     "FILM 170A": 21853,
     "FILM 170B": 21854,
     "FILM 171A": 21855,
     "FILM 171S": 23244,
     "FILM 172": 21856,
     "FILM 185D": 21857,
     "FILM 185S": 22762,
     "FILM 194C": 21858,
     "FILM 200C": 22940,
     "FILM 224": 22850,
     "FILM 237": 23194,
     "FMST 1": 22605,
     "FMST 40": 22892,
     "FMST 75": 23820,
     "FMST 80S": 22225,
     "FMST 110Q": 23903,
     "FMST 188": 23236,
     "FMST 194O": 22923,
     "FMST 200": 23029,
     "FMST 203": 23939,
     "FMST 204": 22701,
     "FMST 264": 21932,
     "FREN 1": 21861,
     "FREN 2": 21862,
     "FREN 3": 21863,
     "FREN 4": 21864,
     "FREN 5": 21865,
     "FREN 111": 21866,
     "GAME 200": 24053,
     "GAME 230": 23214,
     "GAME 235": 24054,
     "GAME 280A": 24055,
     "GERM 1": 21869,
     "GERM 4": 21870,
     "GREE 1": 21871,
     "HAVC 24": 22897,
     "HAVC 40": 21872,
     "HAVC 45": 22965,
     "HAVC 70": 21879,
     "HAVC 116": 22719,
     "HAVC 141K": 21881,
     "HAVC 143E": 23120,
     "HAVC 160A": 21880,
     "HAVC 180A": 23760,
     "HAVC 191P": 23360,
     "HAVC 191W": 23321,
     "HAVC 201A": 22874,
     "HAVC 204": 23037,
     "HAVC 205": 23225,
     "HAVC 233": 23006,
     "HEBR 1": 21888,
     "HIS 10A": 21890,
     "HIS 11A": 21900,
     "HIS 40B": 23758,
     "HIS 41": 21903,
     "HIS 70B": 21895,
     "HIS 77": 23284,
     "HIS 100": 21908,
     "HIS 101E": 23335,
     "HIS 110A": 21910,
     "HIS 116A": 23293,
     "HIS 117": 22742,
     "HIS 128": 21915,
     "HIS 137A": 21912,
     "HIS 140D": 22653,
     "HIS 150F": 23789,
     "HIS 158A": 23916,
     "HIS 158C": 23128,
     "HIS 159C": 23124,
     "HIS 167A": 23088,
     "HIS 172A": 21909,
     "HIS 190A": 21923,
     "HIS 196H": 23014,
     "HIS 200": 21924,
     "HIS 210B": 21926,
     "HIS 230B": 21925,
     "HIS 260": 23028,
     "HIS 280A": 21927,
     "HIS 280B": 21928,
     "HIS 280C": 21929,
     "HISC 80O": 23294,
     "HISC 120": 23825,
     "HISC 203A": 21930,
     "HISC 226": 23804,
     "HISC 232": 23803,
     "HISC 240": 23566,
     "HISC 264": 21931,
     "ITAL 1": 21938,
     "ITAL 4": 21939,
     "ITAL 100": 23138,
     "JAPN 1": 24415,
     "JAPN 4": 21947,
     "JAPN 103": 21948,
     "JWST 77": 23287,
     "KRSG 1": 24384,
     "KRSG 12A": 21949,
     "KRSG 18": 23188,
     "KRSG 25": 23036,
     "LAAD 210": 22909,
     "LALS 1": 21950,
     "LALS 80S": 23362,
     "LALS 90": 23239,
     "LALS 95": 24379,
     "LALS 100": 22776,
     "LALS 122": 22889,
     "LALS 130": 23224,
     "LALS 143J": 23942,
     "LALS 171": 23259,
     "LALS 172": 22901,
     "LALS 180": 21964,
     "LALS 194R": 22858,
     "LALS 200": 21965,
     "LALS 208": 24260,
     "LALS 292": 24297,
     "LATN 1": 21967,
     "LGST 10": 21968,
     "LGST 105C": 22377,
     "LGST 109": 22714,
     "LGST 110": 23356,
     "LGST 111B": 22629,
     "LGST 111C": 22763,
     "LGST 117": 23274,
     "LGST 120C": 22388,
     "LGST 128I": 22517,
     "LGST 159": 21975,
     "LGST 196": 21976,
     "LING 50": 21977,
     "LING 53": 21991,
     "LING 80D": 21996,
     "LING 102": 21997,
     "LING 112": 21987,
     "LING 114A": 22002,
     "LING 140": 22003,
     "LING 151": 22664,
     "LING 154": 22857,
     "LING 211": 22006,
     "LING 221": 22007,
     "LING 229": 22008,
     "LING 231": 22009,
     "LING 240": 22010,
     "LING 259": 22879,
     "LIT 1": 22011,
     "LIT 61P": 22016,
     "LIT 61W": 23788,
     "LIT 61X": 23341,
     "LIT 61Z": 22049,
     "LIT 80H": 23299,
     "LIT 90": 22031,
     "LIT 91A": 22033,
     "LIT 91B": 22034,
     "LIT 120F": 23683,
     "LIT 125H": 23312,
     "LIT 126F": 22040,
     "LIT 130D": 23219,
     "LIT 133I": 23313,
     "LIT 135E": 22051,
     "LIT 146B": 22026,
     "LIT 146F": 23314,
     "LIT 151G": 23928,
     "LIT 155H": 22043,
     "LIT 155N": 23315,
     "LIT 165C": 23778,
     "LIT 167E": 22947,
     "LIT 168A": 23316,
     "LIT 169A": 23317,
     "LIT 179A": 22035,
     "LIT 179B": 22036,
     "LIT 182J": 23350,
     "LIT 183B": 23117,
     "LIT 184D": 22038,
     "LIT 186B": 22039,
     "LIT 188H": 22620,
     "LIT 189C": 23048,
     "LIT 189S": 22050,
     "LIT 190I": 22622,
     "LIT 190Y": 22995,
     "LIT 200": 22023,
     "LIT 201": 22024,
     "LIT 222": 22025,
     "LIT 250": 22052,
     "LIT 251": 22053,
     "LIT 279A": 23092,
     "LIT 282D": 22037,
     "MATH 2": 22066,
     "MATH 2T": 23193,
     "MATH 3": 22081,
     "MATH 11A": 22093,
     "MATH 11B": 22100,
     "MATH 19A": 22118,
     "MATH 19B": 22131,
     "MATH 20A": 23676,
     "MATH 21": 22141,
     "MATH 23A": 22155,
     "MATH 23B": 22165,
     "MATH 24": 22170,
     "MATH 100": 24345,
     "MATH 101": 22175,
     "MATH 105A": 22180,
     "MATH 111A": 22183,
     "MATH 117": 22189,
     "MATH 128A": 22193,
     "MATH 134": 23679,
     "MATH 152": 23281,
     "MATH 189": 24292,
     "MATH 200": 22196,
     "MATH 203": 22659,
     "MATH 204": 22197,
     "MATH 208": 22200,
     "MATH 211": 22198,
     "MATH 213A": 22199,
     "MATH 238": 22201,
     "MATH 239": 22202,
     "MATH 292": 22203,
     "MERR 1": 23613,
     "MERR 3L": 23269,
     "MERR 85B": 22204,
     "MERR 85C": 22764,
     "MERR 90": 23066,
     "MERR 183F": 23220,
     "METX 119": 21069,
     "METX 119L": 21075,
     "METX 200": 22772,
     "METX 201": 21817,
     "METX 281C": 22718,
     "METX 281M": 22839,
     "METX 281O": 21132,
     "METX 281S": 21146,
     "METX 281V": 22910,
     "METX 281Y": 21818,
     "METX 292": 21819,
     "MUSC 1C": 22205,
     "MUSC 2": 22206,
     "MUSC 3": 22207,
     "MUSC 5A": 22210,
     "MUSC 5B": 22211,
     "MUSC 5C": 22212,
     "MUSC 8A": 22213,
     "MUSC 8B": 23231,
     "MUSC 9": 22214,
     "MUSC 10": 22826,
     "MUSC 11A": 22215,
     "MUSC 11B": 22223,
     "MUSC 11D": 22699,
     "MUSC 12B": 23320,
     "MUSC 30A": 22216,
     "MUSC 51": 22217,
     "MUSC 55": 23275,
     "MUSC 60": 22221,
     "MUSC 75": 23363,
     "MUSC 80C": 22222,
     "MUSC 80S": 22224,
     "MUSC 80Z": 23086,
     "MUSC 81M": 23322,
     "MUSC 101C": 22227,
     "MUSC 102": 22688,
     "MUSC 103": 22785,
     "MUSC 121": 22229,
     "MUSC 125": 22228,
     "MUSC 130": 22226,
     "MUSC 159A": 22230,
     "MUSC 163": 22231,
     "MUSC 164": 22232,
     "MUSC 166": 22233,
     "MUSC 167": 22234,
     "MUSC 200": 22235,
     "MUSC 201": 22236,
     "MUSC 219": 22695,
     "MUSC 252": 22707,
     "OAKS 1": 23657,
     "OAKS 73B": 23021,
     "OAKS 151A": 23064,
     "OAKS 151B": 23065,
     "OCEA 1": 22238,
     "OCEA 80A": 22239,
     "OCEA 90": 23108,
     "OCEA 200": 22246,
     "OCEA 211": 22717,
     "OCEA 213": 22753,
     "OCEA 280": 22248,
     "OCEA 290C": 22249,
     "OCEA 292": 22250,
     "OCEA 296": 22251,
     "PBS 101": 23941,
     "PHIL 9": 22252,
     "PHIL 11": 22257,
     "PHIL 23": 23200,
     "PHIL 80G": 21243,
     "PHIL 100A": 22279,
     "PHIL 106": 22284,
     "PHIL 122": 22285,
     "PHIL 143": 22964,
     "PHIL 190": 23026,
     "PHIL 235": 23568,
     "PHIL 280": 22775,
     "PHIL 281": 23180,
     "PHIL 290P": 22793,
     "PHYE 5A": 20820,
     "PHYE 5B": 20821,
     "PHYE 5C": 20822,
     "PHYE 5G": 20823,
     "PHYE 5R": 23369,
     "PHYE 5S": 20818,
     "PHYE 5T": 20868,
     "PHYE 9B": 20829,
     "PHYE 9C": 20875,
     "PHYE 9D": 20872,
     "PHYE 9H": 23371,
     "PHYE 9J": 23367,
     "PHYE 9K": 20864,
     "PHYE 9S": 20871,
     "PHYE 9T": 20873,
     "PHYE 9X": 20874,
     "PHYE 15B": 20883,
     "PHYE 15H": 20832,
     "PHYE 15N": 20835,
     "PHYE 15T": 20889,
     "PHYE 20A": 20840,
     "PHYE 20B": 20866,
     "PHYE 20C": 20886,
     "PHYE 20D": 20843,
     "PHYE 20F": 20844,
     "PHYE 25A": 20876,
     "PHYE 25B": 20877,
     "PHYE 25C": 20878,
     "PHYE 28K": 23368,
     "PHYE 30G": 23919,
     "PHYE 30H": 20880,
     "PHYE 30J": 20884,
     "PHYE 30L": 23378,
     "PHYE 30N": 20879,
     "PHYE 43A": 20858,
     "PHYE 209B": 20885,
     "PHYS 5A": 22287,
     "PHYS 5C": 22290,
     "PHYS 5D": 22293,
     "PHYS 5L": 22306,
     "PHYS 5N": 24127,
     "PHYS 6A": 22314,
     "PHYS 6C": 22317,
     "PHYS 6L": 23857,
     "PHYS 6N": 22349,
     "PHYS 102": 22992,
     "PHYS 105": 22350,
     "PHYS 107": 22354,
     "PHYS 116C": 22355,
     "PHYS 133": 24306,
     "PHYS 135A": 22618,
     "PHYS 139B": 22361,
     "PHYS 171": 22362,
     "PHYS 182": 23008,
     "PHYS 202": 24363,
     "PHYS 210": 22364,
     "PHYS 212": 22365,
     "PHYS 217": 22366,
     "PHYS 221A": 22367,
     "PHYS 231": 22368,
     "PHYS 291A": 22369,
     "PHYS 291C": 22370,
     "PHYS 291D": 22803,
     "PHYS 291E": 22801,
     "PHYS 291F": 22802,
     "PHYS 291G": 22804,
     "PHYS 292": 22371,
     "POLI 3": 22786,
     "POLI 21": 23921,
     "POLI 105C": 22372,
     "POLI 110": 22382,
     "POLI 111B": 23327,
     "POLI 118": 23022,
     "POLI 120C": 22383,
     "POLI 125": 22761,
     "POLI 128": 23039,
     "POLI 129": 22393,
     "POLI 140A": 22394,
     "POLI 143": 22399,
     "POLI 144": 22925,
     "POLI 160D": 22402,
     "POLI 165": 22400,
     "POLI 174": 22401,
     "POLI 185": 23123,
     "POLI 186": 23823,
     "POLI 190H": 22407,
     "POLI 190L": 22408,
     "POLI 190P": 22409,
     "POLI 222": 22926,
     "POLI 255": 23770,
     "PORT 1A": 22410,
     "PORT 60A": 22411,
     "PORT 65B": 22412,
     "PRTR 1": 24327,
     "PRTR 41I": 22715,
     "PSYC 1": 22413,
     "PSYC 10": 22436,
     "PSYC 20A": 22441,
     "PSYC 40": 22448,
     "PSYC 100": 22427,
     "PSYC 104": 23821,
     "PSYC 112": 23079,
     "PSYC 114": 23226,
     "PSYC 119T": 23567,
     "PSYC 124": 23828,
     "PSYC 125": 22449,
     "PSYC 129": 22456,
     "PSYC 138": 23054,
     "PSYC 139H": 22795,
     "PSYC 139K": 23023,
     "PSYC 140H": 22987,
     "PSYC 146": 23822,
     "PSYC 150": 22461,
     "PSYC 153": 22462,
     "PSYC 159I": 23858,
     "PSYC 159R": 23198,
     "PSYC 167": 22467,
     "PSYC 170": 23896,
     "PSYC 171": 22472,
     "PSYC 172": 24285,
     "PSYC 175": 23326,
     "PSYC 191A": 22477,
     "PSYC 204": 22478,
     "PSYC 214B": 22480,
     "PSYC 224A": 22481,
     "PSYC 225A": 22482,
     "PSYC 230": 22483,
     "PSYC 231": 22484,
     "PSYC 242": 22485,
     "PSYC 244A": 22486,
     "PSYC 290B": 22487,
     "RUSS 1": 22488,
     "SCIC 201A": 22489,
     "SCIC 202": 22490,
     "SOCD 200": 22689,
     "SOCD 201A": 22712,
     "SOCD 204": 22700,
     "SOCD 294A": 22702,
     "SOCY 1": 22493,
     "SOCY 3A": 22518,
     "SOCY 15": 22500,
     "SOCY 30A": 22509,
     "SOCY 105A": 22527,
     "SOCY 111": 22536,
     "SOCY 127P": 23242,
     "SOCY 128I": 22516,
     "SOCY 129": 23364,
     "SOCY 136": 23365,
     "SOCY 152": 22539,
     "SOCY 172": 22540,
     "SOCY 178": 22541,
     "SOCY 196G": 23805,
     "SOCY 201": 22542,
     "SOCY 203": 22543,
     "SOCY 290": 22544,
     "SPAN 1": 22548,
     "SPAN 2": 22552,
     "SPAN 3": 22557,
     "SPAN 4": 22561,
     "SPAN 5": 22562,
     "SPAN 5M": 22564,
     "SPAN 6": 22565,
     "SPAN 105": 23051,
     "SPAN 150": 22898,
     "SPAN 151": 22899,
     "SPAN 156M": 22570,
     "SPHS 4": 22569,
     "SPHS 115": 23168,
     "STEV 1": 23815,
     "STEV 11A": 23217,
     "STEV 80H": 22571,
     "STEV 90": 23067,
     "STEV 96": 23814,
     "THEA 10": 22572,
     "THEA 12": 22573,
     "THEA 14": 24282,
     "THEA 20": 22574,
     "THEA 22": 22583,
     "THEA 31C": 23777,
     "THEA 36": 22584,
     "THEA 37": 23859,
     "THEA 40": 22585,
     "THEA 50": 22586,
     "THEA 55A": 22671,
     "THEA 55B": 22684,
     "THEA 61A": 22796,
     "THEA 80L": 22587,
     "THEA 80U": 23261,
     "THEA 80Z": 22598,
     "THEA 106": 22890,
     "THEA 126": 22599,
     "THEA 151": 22600,
     "THEA 157": 22601,
     "THEA 161C": 23929,
     "THEA 161D": 22602,
     "THEA 161T": 22603,
     "THEA 185": 22604,
     "THEA 290A": 23018,
     "TIM 50": 21933,
     "TIM 101": 21934,
     "TIM 105": 22609,
     "TIM 166A": 22835,
     "TIM 205": 22610,
     "TIM 209": 22752,
     "TIM 280I": 22759,
     "TIM 280S": 23769,
     "UCDC 194A": 22491,
     "UCDC 194B": 22492,
     "WRIT 1A": 23765,
     "WRIT 2": 23767,
     "WRIT 23": 22741,
     "WRIT 25": 23149,
     "WRIT 26": 23165,
     "WRIT 27": 23167,
     "WRIT 169": 22608
}